utils/__init__.py
utils/src/__init__.py
utils/src/compute.py
opencv_statistical_tools-0.3.0.dist-info/LICENSE
opencv_statistical_tools-0.3.0.dist-info/METADATA
opencv_statistical_tools-0.3.0.dist-info/WHEEL
opencv_statistical_tools-0.3.0.dist-info/top_level.txt
opencv_statistical_tools-0.3.0.dist-info/RECORD
