Metadata-Version: 2.1
Name: opencv-statistical-tools
Version: 0.3.0
Summary: An OpenCV utility package for additional utility functions for probability and statistical operations.
Home-page: https://github.com/ArjanCodes/2023-package
Author: Stephen Hudson
Author-email: arjan@arjancodes.com
License: MIT
Platform: UNKNOWN
Classifier: License :: OSI Approved :: MIT License
Classifier: Programming Language :: Python :: 3.10
Classifier: Operating System :: OS Independent
Requires-Python: >=3.6
License-File: LICENSE
Requires-Dist: opencv-python (>=4.5.3)
Requires-Dist: numpy (>=1.21.0)
Provides-Extra: dev
Requires-Dist: pytest (>=7.0) ; extra == 'dev'
Requires-Dist: twine (>=4.0.2) ; extra == 'dev'
